pktlab/__init__.py
pktlab/_scripts/__init__.py
pktlab/_scripts/ppksman_cmd.py
pktlab/_scripts/subcmd_gen.py
pktlab/_scripts/subcmd_import.py
pktlab/_scripts/subcmd_init.py
pktlab/_scripts/subcmd_list.py
pktlab/_scripts/subcmd_rm.py
pktlab/_scripts/subcmd_show.py
pktlab/const/__init__.py
pktlab/legacy/__init__.py
pktlab/pktif/__init__.py
pktlab/ppks/AbstractPPKSKeyManager.py
pktlab/ppks/AbstractPPKSStateManager.py
pktlab/ppks/LocalFSPPKSKeyManager.py
pktlab/ppks/LocalFSPPKSStateManager.py
pktlab/ppks/PPKSManager.py
pktlab/ppks/PacketLabConstants.py
pktlab/ppks/__init__.py
pktlab/ppks/_utils.py
pktlab/ppks/extensions/__init__.py
pktlab/ppks/extensions/exts.py
pktlab-1.0.4.dist-info/METADATA
pktlab-1.0.4.dist-info/WHEEL
pktlab-1.0.4.dist-info/entry_points.txt
pktlab-1.0.4.dist-info/top_level.txt
pktlab-1.0.4.dist-info/RECORD
