Metadata-Version: 2.1
Name: pktlab
Version: 1.0.4
Summary: Python libraries and utilities for the PacketLab network measurement framework (including the PacketLab Public Key System Commandline Tools)
Home-page: UNKNOWN
Author: TB Yan, Michael Chen, Anthea Chen, Tianyang Zhou
License: UNKNOWN
Platform: UNKNOWN
Classifier: Development Status :: 4 - Beta
Classifier: Operating System :: OS Independent
Classifier: Programming Language :: Python :: 3 :: Only
Classifier: Topic :: Software Development :: Libraries
Classifier: Topic :: Utilities
Requires-Python: >=3.7
Requires-Dist: asn1tools (>=0.160)
Requires-Dist: cryptography (>=42.0.0)
Requires-Dist: pyopenssl (>=23.2.0)
